mm_zksync/__init__.py
mm_zksync/abi.py
mm_zksync/rpc.py
mm_zksync/abi/zksync.json
mm_zksync-0.0.2.dist-info/METADATA
mm_zksync-0.0.2.dist-info/WHEEL
mm_zksync-0.0.2.dist-info/RECORD
