Metadata-Version: 2.4
Name: mm-zksync
Version: 0.0.2
Requires-Python: >=3.12
Requires-Dist: mm-eth~=0.2.4
